scraper/constants.py
scraper/main.py
scraper/utils.py
coursera_scraper-0.1.3.dist-info/METADATA
coursera_scraper-0.1.3.dist-info/WHEEL
coursera_scraper-0.1.3.dist-info/top_level.txt
coursera_scraper-0.1.3.dist-info/RECORD
