Metadata-Version: 2.1
Name: coursera-scraper
Version: 0.1.3
Summary: This Python script utilizes Selenium to scrape data from Coursera, providing detailed information about various courses such as link, title, rating, recent views, students enrolled, time requirement, skills, learner count, difficulty level, duration, and sub-course details.
Home-page: https://github.com/talhakhalidmtk/coursera-scraper
Author: Talha Khalid
Author-email: talhakhalidmtk@gmail.com
Classifier: Programming Language :: Python :: 3
Classifier: License :: OSI Approved :: MIT License
Classifier: Operating System :: OS Independent
Requires-Python: >=3.6
Requires-Dist: pandas
Requires-Dist: selenium
Requires-Dist: webdriver-manager
